{
  "events": [
    {
      "name": "AVICII",
      "description": "AVICII",
      "date": "2025-11-27",
      "time": "16:40",
      "ticketPrice": 1000,
      "availableTickets": 1000,
      "clubId": 1,
      "id": 1
    },
    {
      "name": "Swedish House Mafia",
      "description": "A party to remember",
      "date": "2026-01-16",
      "time": "18:00",
      "ticketPrice": 500,
      "availableTickets": 1000,
      "clubId": 1,
      "id": 2
    }
  ],
  "clubs": [
    {
      "name": "EDM Club",
      "location": "Linköping",
      "capacity": 16000,
      "id": 1
    }
  ],
  "bookings": []
}